espaloma_charge/__init__.py
espaloma_charge/_version.py
espaloma_charge/antechamber_utils.py
espaloma_charge/app.py
espaloma_charge/cli.py
espaloma_charge/models.py
espaloma_charge/openff_wrapper.py
espaloma_charge/utils.py
espaloma_charge-0.0.8.dist-info/LICENSE
espaloma_charge-0.0.8.dist-info/METADATA
espaloma_charge-0.0.8.dist-info/WHEEL
espaloma_charge-0.0.8.dist-info/entry_points.txt
espaloma_charge-0.0.8.dist-info/top_level.txt
espaloma_charge-0.0.8.dist-info/RECORD
