Metadata-Version: 2.1
Name: espaloma-charge
Version: 0.0.8
Author: Yuanqing Wang
Author-email: wangyq@wangyq.net
License: MIT
License-File: LICENSE
Requires-Dist: dgl
Requires-Dist: torch
Requires-Dist: numpy
Requires-Dist: rdkit
